{
  "users": {
    "-MwTcbE3LffvXRaMIbxd": {
      "fornavn": "Heidi",
      "efternavn": "Astrup",
      "fødselsdato": "2005-03-10",
      "image": "heidi.img",
      "rating": 961,
      "sejre": 5,
      "spilledekampe": 7,
      "adresse": "Hervejen 14",
      "mail": "heidi@kabelmail.dk",
      "password": "Bruger45",
      "facebook": "heidiFB",
      "harlicens": true,
      "kid": "-KeScDIH3JeJ61334gps",
      "hid": "-HnAd4o6AtIlkW2SCf6R"
    },
    "-MQdCUBJ0rx3mIp7GUI9": {
      "fornavn": "Mads",
      "efternavn": "Jensen",
      "fødselsdato": "2004-06-15",
      "image": "mads.img",
      "rating": 850,
      "sejre": 3,
      "spilledekampe": 5,
      "adresse": "Skovvej 10",
      "mail": "mads@kabelmail.dk",
      "password": "Bruger46",
      "facebook": "madsFB",
      "harlicens": true,
      "kid": "-KeScDIH3JeJ61334gps",
      "hid": "-HnAd4o6AtIlkW2SCf6R"
    },
    "-MAv2vaIaj4EEGJScKea": {
      "fornavn": "Sofie",
      "efternavn": "Larsen",
      "fødselsdato": "2006-01-20",
      "image": "sofie.img",
      "rating": 910,
      "sejre": 4,
      "spilledekampe": 6,
      "adresse": "Engvej 5",
      "mail": "sofie@kabelmail.dk",
      "password": "Bruger47",
      "facebook": "sofieFB",
      "harlicens": true,
      "kid": "-KeScDIH3JeJ61334gps",
      "hid": "-HnAd4o6AtIlkW2SCf6R"
    },
    "-MZIwziONH00eOnAZWer": {
      "fornavn": "Jonas",
      "efternavn": "Hansen",
      "fødselsdato": "2003-11-12",
      "image": "jonas.img",
      "rating": 870,
      "sejre": 2,
      "spilledekampe": 4,
      "adresse": "Bakkevej 8",
      "mail": "jonas@kabelmail.dk",
      "password": "Bruger48",
      "facebook": "jonasFB",
      "harlicens": true,
      "kid": "-KeScDIH3JeJ61334gps",
      "hid": "-HDSqi794AwzkeclR1lv"
    },
    "-MeG3eLMQaFnhvHuZVtq": {
      "fornavn": "Emma",
      "efternavn": "Nielsen",
      "fødselsdato": "2005-09-25",
      "image": "emma.img",
      "rating": 920,
      "sejre": 6,
      "spilledekampe": 8,
      "adresse": "Søvej 3",
      "mail": "emma@kabelmail.dk",
      "password": "Bruger49",
      "facebook": "emmaFB",
      "harlicens": true,
      "kid": "-KeScDIH3JeJ61334gps",
      "hid": "-HDSqi794AwzkeclR1lv"
    },
    "-M2RCV8bDfsnnnER4Q6A": {
      "fornavn": "Frederik",
      "efternavn": "Olsen",
      "fødselsdato": "2004-04-18",
      "image": "frederik.img",
      "rating": 890,
      "sejre": 3,
      "spilledekampe": 5,
      "adresse": "Markvej 12",
      "mail": "frederik@kabelmail.dk",
      "password": "Bruger50",
      "facebook": "frederikFB",
      "harlicens": true,
      "kid": "-KeScDIH3JeJ61334gps",
      "hid": "-HDSqi794AwzkeclR1lv"
    },
    "-Me32cBZPnkYatPDJHcA": {
      "fornavn": "Frederik",
      "efternavn": "Olsen",
      "fødselsdato": "2004-04-18",
      "image": "frederik.img",
      "rating": 890,
      "sejre": 3,
      "spilledekampe": 5,
      "adresse": "Markvej 12",
      "mail": "frederik@kabelmail.dk",
      "password": "Bruger50",
      "facebook": "frederikFB",
      "harlicens": true,
      "kid": "-K4O0aPyG0NjMc875nk4",
      "hid": "-HiOIizyRdCJg8LJf56f"
    },
    "-M9N7DaDeCifLFMpcHib": {
      "fornavn": "Frederik",
      "efternavn": "Olsen",
      "fødselsdato": "2004-04-18",
      "image": "frederik.img",
      "rating": 890,
      "sejre": 3,
      "spilledekampe": 5,
      "adresse": "Markvej 12",
      "mail": "frederik@kabelmail.dk",
      "password": "Bruger50",
      "facebook": "frederikFB",
      "harlicens": true,
      "kid": "-K4O0aPyG0NjMc875nk4",
      "hid": "-HiOIizyRdCJg8LJf56f"
    },
    "-Mh9WSJ71cft1N91knLY": {
      "fornavn": "Frederik",
      "efternavn": "Olsen",
      "fødselsdato": "2004-04-18",
      "image": "frederik.img",
      "rating": 890,
      "sejre": 3,
      "spilledekampe": 5,
      "adresse": "Markvej 12",
      "mail": "frederik@kabelmail.dk",
      "password": "Bruger50",
      "facebook": "frederikFB",
      "harlicens": true,
      "kid": "-K4O0aPyG0NjMc875nk4",
      "hid": "-HiOIizyRdCJg8LJf56f"
    },
    "-MP7HlghOXxda3w5khAF": {
      "fornavn": "Frederik",
      "efternavn": "Olsen",
      "fødselsdato": "2004-04-18",
      "image": "frederik.img",
      "rating": 890,
      "sejre": 3,
      "spilledekampe": 5,
      "adresse": "Markvej 12",
      "mail": "frederik@kabelmail.dk",
      "password": "Bruger50",
      "facebook": "frederikFB",
      "harlicens": true,
      "kid": "-K4O0aPyG0NjMc875nk4",
      "hid": "-HGv2lmeMtURsQHspuZC"
    },
    "-MXELgAr16bdEXe9j8o9": {
      "fornavn": "Frederik",
      "efternavn": "Olsen",
      "fødselsdato": "2004-04-18",
      "image": "frederik.img",
      "rating": 890,
      "sejre": 3,
      "spilledekampe": 5,
      "adresse": "Markvej 12",
      "mail": "frederik@kabelmail.dk",
      "password": "Bruger50",
      "facebook": "frederikFB",
      "harlicens": true,
      "kid": "-K4O0aPyG0NjMc875nk4",
      "hid": "-HGv2lmeMtURsQHspuZC"
    },
    "-MPfbmeQnqLWbE48Rd5L": {
      "fornavn": "Frederik",
      "efternavn": "Olsen",
      "fødselsdato": "2004-04-18",
      "image": "frederik.img",
      "rating": 890,
      "sejre": 3,
      "spilledekampe": 5,
      "adresse": "Markvej 12",
      "mail": "frederik@kabelmail.dk",
      "password": "Bruger50",
      "facebook": "frederikFB",
      "harlicens": true,
      "kid": "-K4O0aPyG0NjMc875nk4",
      "hid": "-HGv2lmeMtURsQHspuZC"
    },
    "-MqxkKm0eYWx0QK34wnM": {
      "fornavn": "Frederik",
      "efternavn": "Olsen",
      "fødselsdato": "2004-04-18",
      "image": "frederik.img",
      "rating": 890,
      "sejre": 3,
      "spilledekampe": 5,
      "adresse": "Markvej 12",
      "mail": "frederik@kabelmail.dk",
      "password": "Bruger50",
      "facebook": "frederikFB",
      "harlicens": true,
      "kid": "-KEiZyGpLmRRPNuXAIW1",
      "hid": "-Hi2WQJ8YdlU3uWhfttU"
    },
    "-MsZEx3Z8rtOCVmfd7wJ": {
      "fornavn": "Frederik",
      "efternavn": "Olsen",
      "fødselsdato": "2004-04-18",
      "image": "frederik.img",
      "rating": 890,
      "sejre": 3,
      "spilledekampe": 5,
      "adresse": "Markvej 12",
      "mail": "frederik@kabelmail.dk",
      "password": "Bruger50",
      "facebook": "frederikFB",
      "harlicens": true,
      "kid": "-KEiZyGpLmRRPNuXAIW1",
      "hid": "-Hi2WQJ8YdlU3uWhfttU"
    },
    "-MBSkIAIJ5jHLRocTN15": {
      "fornavn": "Frederik",
      "efternavn": "Olsen",
      "fødselsdato": "2004-04-18",
      "image": "frederik.img",
      "rating": 890,
      "sejre": 3,
      "spilledekampe": 5,
      "adresse": "Markvej 12",
      "mail": "frederik@kabelmail.dk",
      "password": "Bruger50",
      "facebook": "frederikFB",
      "harlicens": true,
      "kid": "-KEiZyGpLmRRPNuXAIW1",
      "hid": "-Hi2WQJ8YdlU3uWhfttU"
    },
    "-MpN5kZmNwktWwpM5c6e": {
      "fornavn": "Frederik",
      "efternavn": "Olsen",
      "fødselsdato": "2004-04-18",
      "image": "frederik.img",
      "rating": 890,
      "sejre": 3,
      "spilledekampe": 5,
      "adresse": "Markvej 12",
      "mail": "frederik@kabelmail.dk",
      "password": "Bruger50",
      "facebook": "frederikFB",
      "harlicens": true,
      "kid": "-KEiZyGpLmRRPNuXAIW1",
      "hid": "-HcCwVVsyQWhMvH3kfrn"
    },
    "-MNTkilvTUgLirWBlhus": {
      "fornavn": "Frederik",
      "efternavn": "Olsen",
      "fødselsdato": "2004-04-18",
      "image": "frederik.img",
      "rating": 890,
      "sejre": 3,
      "spilledekampe": 5,
      "adresse": "Markvej 12",
      "mail": "frederik@kabelmail.dk",
      "password": "Bruger50",
      "facebook": "frederikFB",
      "harlicens": true,
      "kid": "-KEiZyGpLmRRPNuXAIW1",
      "hid": "-HcCwVVsyQWhMvH3kfrn"
    },
    "-Mpv40hz6jbWzaAZplC3": {
      "fornavn": "Frederik",
      "efternavn": "Olsen",
      "fødselsdato": "2004-04-18",
      "image": "frederik.img",
      "rating": 890,
      "sejre": 3,
      "spilledekampe": 5,
      "adresse": "Markvej 12",
      "mail": "frederik@kabelmail.dk",
      "password": "Bruger50",
      "facebook": "frederikFB",
      "harlicens": true,
      "kid": "-KEiZyGpLmRRPNuXAIW1",
      "hid": "-HcCwVVsyQWhMvH3kfrn"
    },
    "-MTIY5hrKMlAZVPbnCG4": {
      "fornavn": "Frederik",
      "efternavn": "Olsen",
      "fødselsdato": "2004-04-18",
      "image": "frederik.img",
      "rating": 890,
      "sejre": 3,
      "spilledekampe": 5,
      "adresse": "Markvej 12",
      "mail": "frederik@kabelmail.dk",
      "password": "Bruger50",
      "facebook": "frederikFB",
      "harlicens": true,
      "kid": "-K20RrNJXDMNNtzZRUGL",
      "hid": "-H0thTJcPDJV2beGCK0y"
    },
    "-MNuhUT6aw3IUfmbzE6a": {
      "fornavn": "Frederik",
      "efternavn": "Olsen",
      "fødselsdato": "2004-04-18",
      "image": "frederik.img",
      "rating": 890,
      "sejre": 3,
      "spilledekampe": 5,
      "adresse": "Markvej 12",
      "mail": "frederik@kabelmail.dk",
      "password": "Bruger50",
      "facebook": "frederikFB",
      "harlicens": true,
      "kid": "-K20RrNJXDMNNtzZRUGL",
      "hid": "-H0thTJcPDJV2beGCK0y"
    },
    "-MkOlklcYDidKJKVchT8": {
      "fornavn": "Frederik",
      "efternavn": "Olsen",
      "fødselsdato": "2004-04-18",
      "image": "frederik.img",
      "rating": 890,
      "sejre": 3,
      "spilledekampe": 5,
      "adresse": "Markvej 12",
      "mail": "frederik@kabelmail.dk",
      "password": "Bruger50",
      "facebook": "frederikFB",
      "harlicens": true,
      "kid": "-K20RrNJXDMNNtzZRUGL",
      "hid": "-H0thTJcPDJV2beGCK0y"
    },
    "-MeYXiyeNfVZSB2KWAph": {
      "fornavn": "Frederik",
      "efternavn": "Olsen",
      "fødselsdato": "2004-04-18",
      "image": "frederik.img",
      "rating": 890,
      "sejre": 3,
      "spilledekampe": 5,
      "adresse": "Markvej 12",
      "mail": "frederik@kabelmail.dk",
      "password": "Bruger50",
      "facebook": "frederikFB",
      "harlicens": true,
      "kid": "-K20RrNJXDMNNtzZRUGL",
      "hid": "-HgA12nH5Y1XCfxyUvPj"
    },
    "-MUVQiOkYzHdC2tCtepa": {
      "fornavn": "Frederik",
      "efternavn": "Olsen",
      "fødselsdato": "2004-04-18",
      "image": "frederik.img",
      "rating": 890,
      "sejre": 3,
      "spilledekampe": 5,
      "adresse": "Markvej 12",
      "mail": "frederik@kabelmail.dk",
      "password": "Bruger50",
      "facebook": "frederikFB",
      "harlicens": true,
      "kid": "-K20RrNJXDMNNtzZRUGL",
      "hid": "-HgA12nH5Y1XCfxyUvPj"
    },
    "-M3AWuUKBpfgbvRP9Ld9": {
      "fornavn": "Frederik",
      "efternavn": "Olsen",
      "fødselsdato": "2004-04-18",
      "image": "frederik.img",
      "rating": 890,
      "sejre": 3,
      "spilledekampe": 5,
      "adresse": "Markvej 12",
      "mail": "frederik@kabelmail.dk",
      "password": "Bruger50",
      "facebook": "frederikFB",
      "harlicens": true,
      "kid": "-K20RrNJXDMNNtzZRUGL",
      "hid": "-HgA12nH5Y1XCfxyUvPj"
    }
  },
  "klubber": {
    "-KeScDIH3JeJ61334gps": {
      "lokation": "Jernaldervej 5, 8210 Aarhus V",
      "navn": "Aarhus Bordtennis",
      "hold": ["-HnAd4o6AtIlkW2SCf6R", "-HDSqi794AwzkeclR1lv"],
      "image": "https://aarhusbordtennis.dk/wp-content/uploads/2025/06/logo_uden_baggrund.png"
    },
    "-K4O0aPyG0NjMc875nk4": {
      "lokation": "Viborgvej 20, 8800 Viborg",
      "navn": "Viborg Bordtennis",
      "hold": ["-HiOIizyRdCJg8LJf56f", "-HGv2lmeMtURsQHspuZC"],
      "image": "https://live-376-viborg-ff.umbraco-proxy.com/media/2088/logo-til-skaerm-nyt.jpg?anchor=center&mode=crop&width=492&height=249&rnd=133018281830000000"
    },
    "-KEiZyGpLmRRPNuXAIW1": {
      "lokation": "Odensevej 15, 5000 Odense",
      "navn": "Odense Bordtennis",
      "hold": ["-Hi2WQJ8YdlU3uWhfttU", "-HcCwVVsyQWhMvH3kfrn"],
      "image": "https://obbordtennis.dk/cms/Clubobbordtennis/images/meta/1.png"
    },
    "-K20RrNJXDMNNtzZRUGL": {
      "lokation": "Randersvej 10, 8900 Randers",
      "navn": "Randers Bordtennis",
      "hold": ["-H0thTJcPDJV2beGCK0y", "-HgA12nH5Y1XCfxyUvPj"],
      "image": "https://motivu-uploads.s3.eu-west-1.amazonaws.com/clubs/logos/5537/conversions/randers-badminton-klub-logo-1637494214-thumb.jpg"
    }
  },
  "hold": {
    "-HnAd4o6AtIlkW2SCf6R": {
      "navn": "AABT 1",
      "spillere": [
        "-MwTcbE3LffvXRaMIbxd",
        "-MQdCUBJ0rx3mIp7GUI9",
        "-MAv2vaIaj4EEGJScKea"
      ],
      "sejre": 2,
      "række": 5,
      "pulje": 2
    },
    "-HDSqi794AwzkeclR1lv": {
      "navn": "AABT 2",
      "spillere": [
        "-MZIwziONH00eOnAZWer",
        "-MeG3eLMQaFnhvHuZVtq",
        "-M2RCV8bDfsnnnER4Q6A"
      ],
      "sejre": 1,
      "række": 5,
      "pulje": 2
    },
    "-HiOIizyRdCJg8LJf56f": {
      "navn": "VBT 1",
      "spillere": [
        "-Me32cBZPnkYatPDJHcA",
        "-M9N7DaDeCifLFMpcHib",
        "-Mh9WSJ71cft1N91knLY"
      ],
      "sejre": 1,
      "række": 5,
      "pulje": 2
    },
    "-HGv2lmeMtURsQHspuZC": {
      "navn": "VBT 2",
      "spillere": [
        "-MP7HlghOXxda3w5khAF",
        "-MXELgAr16bdEXe9j8o9",
        "-MPfbmeQnqLWbE48Rd5L"
      ],
      "sejre": 1,
      "række": 5,
      "pulje": 2
    },
    "-Hi2WQJ8YdlU3uWhfttU": {
      "navn": "OBBT 1",
      "spillere": [
        "-MqxkKm0eYWx0QK34wnM",
        "-MsZEx3Z8rtOCVmfd7wJ",
        "-MBSkIAIJ5jHLRocTN15"
      ],
      "sejre": 1,
      "række": 5,
      "pulje": 2
    },
    "-HcCwVVsyQWhMvH3kfrn": {
      "navn": "OBBT 2",
      "spillere": [
        "-MpN5kZmNwktWwpM5c6e",
        "-MNTkilvTUgLirWBlhus",
        "-Mpv40hz6jbWzaAZplC3"
      ],
      "sejre": 1,
      "række": 5,
      "pulje": 2
    },
    "-H0thTJcPDJV2beGCK0y": {
      "navn": "RBT 1",
      "spillere": [
        "-MTIY5hrKMlAZVPbnCG4",
        "-MNuhUT6aw3IUfmbzE6a",
        "-MkOlklcYDidKJKVchT8"
      ],
      "sejre": 1,
      "række": 5,
      "pulje": 2
    },
    "-HgA12nH5Y1XCfxyUvPj": {
      "navn": "RBT 2",
      "spillere": [
        "-MeYXiyeNfVZSB2KWAph",
        "-MUVQiOkYzHdC2tCtepa",
        "-M3AWuUKBpfgbvRP9Ld9"
      ],
      "sejre": 1,
      "række": 5,
      "pulje": 2
    }
  },
  "staevner": {
    "-Spj1FGjQTUUJkqdPUoc": {
      "lokation": "Brabrand Hallerne",
      "dato": "2023-10-06",
      "pris": 150,
      "titel": "Sisu Open",
      "rækker": "Herre junior C",
      "beskrivelse": "A competitive tournament for junior players.",
      "ertilmeldt": true,
      "tilmeldt": ["Herre junior C", "Herre klasse 2"],
      "harnotifikationer": false
    },
    "-SBTdSjTtmIBsP1PqCea": {
      "lokation": "Brabrand Hallerne",
      "dato": "2023-10-06",
      "pris": 150,
      "titel": "Sisu Open",
      "rækker": "Herre junior C",
      "beskrivelse": "A competitive tournament for junior players.",
      "ertilmeldt": true,
      "tilmeldt": ["Herre junior C", "Herre klasse 2"],
      "harnotifikationer": false
    },
    "-SpyRzlczl0AGjIHHLUw": {
      "lokation": "Brabrand Hallerne",
      "dato": "2023-10-06",
      "pris": 150,
      "titel": "Sisu Open",
      "rækker": "Herre junior C",
      "beskrivelse": "A competitive tournament for junior players.",
      "ertilmeldt": true,
      "tilmeldt": ["Herre junior C", "Herre klasse 2"],
      "harnotifikationer": false
    },
    "-SUGWDyz4smaIPsKgSpw": {
      "lokation": "Brabrand Hallerne",
      "dato": "2023-10-06",
      "pris": 150,
      "titel": "Sisu Open",
      "rækker": "Herre junior C",
      "beskrivelse": "A competitive tournament for junior players.",
      "ertilmeldt": true,
      "tilmeldt": ["Herre junior C", "Herre klasse 2"],
      "harnotifikationer": false
    },
    "-SaRURJieZst9QUWqu4T": {
      "lokation": "Brabrand Hallerne",
      "dato": "2023-10-06",
      "pris": 150,
      "titel": "Sisu Open",
      "rækker": "Herre junior C",
      "beskrivelse": "A competitive tournament for junior players.",
      "ertilmeldt": true,
      "tilmeldt": ["Herre junior C", "Herre klasse 2"],
      "harnotifikationer": false
    },
    "-S7VAzf19ERk6MFnuLOM": {
      "lokation": "Brabrand Hallerne",
      "dato": "2023-10-06",
      "pris": 150,
      "titel": "Sisu Open",
      "rækker": "Herre junior C",
      "beskrivelse": "A competitive tournament for junior players.",
      "ertilmeldt": true,
      "tilmeldt": ["Herre junior C", "Herre klasse 2"],
      "harnotifikationer": false
    }
  },
  "kampe": {
    "370439": {
      "hjemmeklub": "-KeScDIH3JeJ61334gps",
      "udeklub": "-K4O0aPyG0NjMc875nk4",
      "hjemmehold": "-HnAd4o6AtIlkW2SCf6R",
      "udehold": "-HiOIizyRdCJg8LJf56f",
      "dato": "2025-12-15",
      "lokation": "Jernaldervej 5, 8210 Aarhus V",
      "tid": "19:00",
      "harResultat": false,
      "serie": 5,
      "pulje": 2,
      "harNotifikationer": false,
      "resultatHjemme": 0,
      "resultatUde": 0
    },
    "370440": {
      "hjemmeklub": "-K4O0aPyG0NjMc875nk4",
      "udeklub": "-KEiZyGpLmRRPNuXAIW1",
      "hjemmehold": "-HiOIizyRdCJg8LJf56f",
      "udehold": "-Hi2WQJ8YdlU3uWhfttU",
      "dato": "2025-12-17",
      "lokation": "Viborgvej 20, 8800 Viborg",
      "tid": "20:00",
      "harResultat": false,
      "serie": 5,
      "pulje": 2,
      "harNotifikationer": false,
      "resultatHjemme": 0,
      "resultatUde": 0
    },
    "370441": {
      "hjemmeklub": "-K20RrNJXDMNNtzZRUGL",
      "udeklub": "-KEiZyGpLmRRPNuXAIW1",
      "hjemmehold": "-Hi2WQJ8YdlU3uWhfttU",
      "udehold": "-H0thTJcPDJV2beGCK0y",
      "dato": "2025-12-18",
      "lokation": "Odensevej 15, 5000 Odense",
      "tid": "18:30",
      "harResultat": false,
      "serie": 5,
      "pulje": 2,
      "harNotifikationer": false,
      "resultatHjemme": 0,
      "resultatUde": 0
    },
    "370442": {
      "hjemmeklub": "-KEiZyGpLmRRPNuXAIW1",
      "udeklub": "-KeScDIH3JeJ61334gps",
      "hjemmehold": "-HgA12nH5Y1XCfxyUvPj",
      "udehold": "-HDSqi794AwzkeclR1lv",
      "dato": "2025-12-19",
      "lokation": "Randersvej 10, 8900 Randers",
      "tid": "19:30",
      "harResultat": false,
      "serie": 5,
      "pulje": 2,
      "harNotifikationer": false,
      "resultatHjemme": 0,
      "resultatUde": 0
    },
    "370443": {
      "hjemmeklub": "-KeScDIH3JeJ61334gps",
      "udeklub": "-KEiZyGpLmRRPNuXAIW1",
      "hjemmehold": "-HDSqi794AwzkeclR1lv",
      "udehold": "-HcCwVVsyQWhMvH3kfrn",
      "dato": "2026-01-04",
      "lokation": "Jernaldervej 5, 8210 Aarhus V",
      "tid": "20:30",
      "harResultat": false,
      "serie": 5,
      "pulje": 2,
      "harNotifikationer": false,
      "resultatHjemme": 0,
      "resultatUde": 0
    },
    "370444": {
      "hjemmeklub": "-K4O0aPyG0NjMc875nk4",
      "udeklub": "-KEiZyGpLmRRPNuXAIW1",
      "hjemmehold": "-HGv2lmeMtURsQHspuZC",
      "udehold": "-HcCwVVsyQWhMvH3kfrn",
      "dato": "2026-01-08",
      "lokation": "Viborgvej 20, 8800 Viborg",
      "tid": "20:00",
      "harResultat": false,
      "serie": 5,
      "pulje": 2,
      "harNotifikationer": false,
      "resultatHjemme": 0,
      "resultatUde": 0
    },
    "370445": {
      "hjemmeklub": "-KEiZyGpLmRRPNuXAIW1",
      "udeklub": "-K4O0aPyG0NjMc875nk4",
      "hjemmehold": "-HcCwVVsyQWhMvH3kfrn",
      "udehold": "-HiOIizyRdCJg8LJf56f",
      "dato": "2026-01-11",
      "lokation": "Odensevej 15, 5000 Odense",
      "tid": "19:30",
      "harResultat": false,
      "serie": 5,
      "pulje": 2,
      "harNotifikationer": false,
      "resultatHjemme": 0,
      "resultatUde": 0
    },
    "370446": {
      "hjemmeklub": "-K20RrNJXDMNNtzZRUGL",
      "udeklub": "-KEiZyGpLmRRPNuXAIW1",
      "hjemmehold": "-HnAd4o6AtIlkW2SCf6R",
      "udehold": "-HiOIizyRdCJg8LJf56f",
      "dato": "2026-01-17",
      "lokation": "Randersvej 10, 8900 Randers",
      "tid": "19:30",
      "harResultat": false,
      "serie": 5,
      "pulje": 2,
      "harNotifikationer": false,
      "resultatHjemme": 0,
      "resultatUde": 0
    },
    "370447": {
      "hjemmeklub": "-KeScDIH3JeJ61334gps",
      "udeklub": "-KEiZyGpLmRRPNuXAIW1",
      "hjemmehold": "-HnAd4o6AtIlkW2SCf6R",
      "udehold": "-Hi2WQJ8YdlU3uWhfttU",
      "dato": "2026-01-22",
      "lokation": "Jernaldervej 5, 8210 Aarhus V",
      "tid": "19:30",
      "harResultat": false,
      "serie": 5,
      "pulje": 2,
      "harNotifikationer": false,
      "resultatHjemme": 0,
      "resultatUde": 0
    },
    "370448": {
      "hjemmeklub": "-KEiZyGpLmRRPNuXAIW1",
      "udeklub": "-KeScDIH3JeJ61334gps",
      "hjemmehold": "-HcCwVVsyQWhMvH3kfrn",
      "udehold": "-HDSqi794AwzkeclR1lv",
      "dato": "2026-01-26",
      "lokation": "Odensevej 15, 5000 Odense",
      "tid": "20:00",
      "harResultat": false,
      "serie": 5,
      "pulje": 2,
      "harNotifikationer": false,
      "resultatHjemme": 0,
      "resultatUde": 0
    }
  }
}
